{
  "createdAt": "2026-04-16T06:32:59.852Z",
  "updatedAt": "2026-04-16T06:32:59.861Z",
  "globalType": "rd-content",
  "eyebrow": "Innowacje i rozwój",
  "title": "Projekty B+R",
  "subtitle": "Innowacja jest motorem naszego wzrostu. Stale inwestujemy w badania i rozwój, aby oferować zaawansowane rozwiązania techniczne wyprzedzające potrzeby przemysłu motoryzacyjnego.",
  "stats": [
    {
      "value": "+15%",
      "label": "Roczna inwestycja w B+R",
      "id": "69e0829bf0ca630001abfc9b"
    },
    {
      "value": "16+",
      "label": "Finansowane projekty",
      "id": "69e0829bf0ca630001abfc9c"
    },
    {
      "value": "3",
      "label": "Centra rozwoju",
      "id": "69e0829bf0ca630001abfc9d"
    }
  ],
  "funders": {
    "label": "Instytucje finansujące",
    "programLabel": "Program europejski",
    "items": [
      {
        "name": "Rząd Aragonii",
        "description": "Projekty współfinansowane przez Rząd Aragonii w ramach programów wsparcia transformacji i rozwoju przemysłowego, z funduszami EFRR.",
        "id": "69e0829bf0ca630001abfc9e"
      },
      {
        "name": "Unia Europejska",
        "description": "Projekty współfinansowane przez Unię Europejską w ramach programów efektywności energetycznej i innowacji przemysłowych.",
        "id": "69e0829bf0ca630001abfc9f"
      }
    ]
  },
  "contact": {
    "title": "Zainteresowany współpracą?",
    "body": "Jeśli jesteś producentem samochodów, dostawcą materiałów lub instytucją akademicką i chcesz zbadać wspólne projekty B+R, skontaktuj się z nami.",
    "cta": "Skontaktuj się"
  },
  "meta": {
    "title": "Projekty B+R – CEFA",
    "description": "Innowacje i rozwój technologiczny w CEFA. Odkryj nasze projekty badawczo-rozwojowe w zakresie materiałów, procesów i komponentów dla przemysłu motoryzacyjnego."
  },
  "id": "69e0829bdecc0cd23fa9b92a"
}
